{
  "1": "2  ¿Por qué están alborotadas las naciones y los pueblos andan tramando cosas inútiles?\r\n",
  "2": " 2  Los reyes de la tierra toman su posición y los altos funcionarios se reúnen como uno solo contra Jehová y contra su ungido.\r\n",
  "3": " 3  Dicen: “¡Rompamos sus cadenas y quitémonos sus cuerdas!”.\r\n",
  "4": " 4  El que está en los cielos, en su trono, se reirá; Jehová se burlará de ellos.\r\n",
  "5": " 5  En ese tiempo, él les hablará en su furia, en su ardiente furia los llenará de terror;",
  "6": "  6  dirá: “Yo mismo he establecido a mi rey en Sion, mi santa montaña”.\r\n",
  "7": " 7  Voy a proclamar el decreto de Jehová; él me dijo: “Tú eres mi hijo; hoy he llegado a ser tu padre.\r\n",
  "8": " 8  Pídemelo, y te daré naciones como herencia y los confines de la tierra como propiedad.\r\n",
  "9": " 9  Las quebrarás con un cetro de hierro y las harás pedazos como a una vasija de barro”.\r\n",
  "10": "10  Así que ahora, reyes, sean perspicaces; acepten la corrección, jueces de la tierra.\r\n",
  "11": "11  Sirvan a Jehová con temor y alégrense con temblor.\r\n",
  "12": "12  Honren al hijo; si no, Dios se indignará y ustedes morirán en el camino, porque su furia se enciende rápidamente.\r\n¡Felices todos los que se refugian en él!"
}