{
  "1": "6  Oh, Jehová, no me reprendas en tu furia y no me corrijas en tu furor.\r\n",
  "2": " 2  Concédeme tu favor, oh, Jehová, porque me estoy debilitando.\r\nSáname, oh, Jehová, porque me tiemblan los huesos.\r\n",
  "3": " 3  Sí, estoy muy inquieto, y te pregunto, oh, Jehová: ¿hasta cuándo será esto así?\r\n",
  "4": " 4  Vuelve, oh, Jehová, y rescátame; sálvame por causa de tu amor leal.\r\n",
  "5": " 5  Porque en la muerte no se hace mención de ti; en la Tumba, ¿quién te alabará?\r\n",
  "6": " 6  Me he agotado de tanto suspirar; toda la noche empapo mi cama de lágrimas; con mi llanto inundo mi lecho.\r\n",
  "7": " 7  Mis ojos se debilitan de tristeza; han perdido su brillo por culpa de todos los que me acosan.\r\n",
  "8": " 8  Apártense de mí, todos los que se comportan con maldad, porque Jehová oirá mi llanto.\r\n",
  "9": " 9  Jehová oirá mi súplica; Jehová aceptará mi oración.\r\n",
  "10": "10  Todos mis enemigos quedarán avergonzados y aterrados; con repentina vergüenza retrocederán."
}